{"lastUsed":1698317604584,"path":"C:\/Users\/d.jakob\/Desktop\/Workspaces\/Java","projectCount":1,"recentFiles":[{"path":"\/danieluebung\/src","parentWorkspace":"C:\/Users\/d.jakob\/Desktop\/Workspaces\/Java","name":"Beispielklasse.java","lastModified":1698317554965,"locationURI":"file:\/C:\/Users\/d.jakob\/Desktop\/Workspaces\/Java\/danieluebung\/src\/Beispielklasse.java"},{"path":"\/danieluebung\/src","parentWorkspace":"C:\/Users\/d.jakob\/Desktop\/Workspaces\/Java","name":"Main.java","lastModified":1698317526224,"locationURI":"file:\/C:\/Users\/d.jakob\/Desktop\/Workspaces\/Java\/danieluebung\/src\/Main.java"}]}